arinrest/__init__.py
arinrest/arinrest.py
arinrest/facility.py
arinrest/common/__init__.py
arinrest/common/connection.py
arinrest/common/enums.py
arinrest/common/exceptions.py
arinrest/common/rsa.py
arinrest/common/utils.py
arinrest/irr/__init__.py
arinrest/irr/route.py
arinrest/rdap/__init__.py
arinrest/rdap/rdap.py
arinrest/rpki/__init__.py
arinrest/rpki/roa.py
arinrest/rpki/rpki.py
arinrest_client-0.2.1.dist-info/LICENSE
arinrest_client-0.2.1.dist-info/METADATA
arinrest_client-0.2.1.dist-info/WHEEL
arinrest_client-0.2.1.dist-info/top_level.txt
arinrest_client-0.2.1.dist-info/zip-safe
arinrest_client-0.2.1.dist-info/RECORD
