Metadata-Version: 2.1
Name: arinrest-client
Version: 0.2.1
Summary: client to interact with the arinrest API
Home-page: https://github.com/jdhall75/arinrest-client
Author: Jason Hall
Author-email: jdhall75@gmail.com
License: The Unlicense (Unlicense)
Keywords: arinrest,setuptools
Classifier: Development Status :: 4 - Beta
Classifier: License :: OSI Approved :: The Unlicense (Unlicense)
Classifier: Programming Language :: Python :: 3.9
Classifier: Programming Language :: Python :: 3.10
Classifier: Programming Language :: Python :: 3.11
License-File: LICENSE
Requires-Dist: requests (>=2.28)
Requires-Dist: pydantic (>=1.10)
Requires-Dist: cryptography (>=38.0.4)
Provides-Extra: dev
Requires-Dist: black ; extra == 'dev'
Requires-Dist: flake8 ; extra == 'dev'
Requires-Dist: typing-extensions ; extra == 'dev'
Requires-Dist: pytest ; extra == 'dev'
Requires-Dist: build ; extra == 'dev'
Requires-Dist: twine ; extra == 'dev'
